infinity25/__init__.py
infinity25/ALL_PRACT_EASY_PY/P1.py
infinity25/ALL_PRACT_EASY_PY/P10.py
infinity25/ALL_PRACT_EASY_PY/P11.py
infinity25/ALL_PRACT_EASY_PY/P12.py
infinity25/ALL_PRACT_EASY_PY/P2.py
infinity25/ALL_PRACT_EASY_PY/P3.py
infinity25/ALL_PRACT_EASY_PY/P4.py
infinity25/ALL_PRACT_EASY_PY/P5.py
infinity25/ALL_PRACT_EASY_PY/P7.py
infinity25/ALL_PRACT_EASY_PY/P8.py
infinity25/ALL_PRACT_EASY_PY/P9.py
infinity25/ALL_PRACT_EASY_PY/p6.py
infinity25/IMPORTANT_DOC/autopostback.docx
infinity25/IMPORTANT_DOC/calender.docx
infinity25/IMPORTANT_DOC/count_current_page.docx
infinity25/IMPORTANT_DOC/date_properties.docx
"infinity25/IMPORTANT_DOC/fibo,cube,fact,money.docx"
infinity25/IMPORTANT_DOC/fibonachi and prime.docx
infinity25/IMPORTANT_DOC/interface.docx
infinity25/IMPORTANT_DOC/user control.docx
infinity25/IMPORTANT_PDF/AJAX PROGRESS CONTROL AND TREE VIEW CONTROL EXAMPLE/ASPX1.pdf
infinity25/IMPORTANT_PDF/AJAX PROGRESS CONTROL AND TREE VIEW CONTROL EXAMPLE/ASPX2.pdf
infinity25/IMPORTANT_PDF/AJAX PROGRESS CONTROL AND TREE VIEW CONTROL EXAMPLE/CS1.pdf
infinity25/IMPORTANT_PDF/AJAX PROGRESS CONTROL AND TREE VIEW CONTROL EXAMPLE/CS2.pdf
infinity25/IMPORTANT_PDF/AJAX PROGRESS CONTROL AND TREE VIEW CONTROL EXAMPLE/SITEMAP2.pdf
infinity25/IMPORTANT_PDF/CONSOLE OPERATION AND CALENDOR CONTROL/ASPX.pdf
infinity25/IMPORTANT_PDF/CONSOLE OPERATION AND CALENDOR CONTROL/CONSOLE.pdf
infinity25/IMPORTANT_PDF/CONSOLE OPERATION AND CALENDOR CONTROL/CS.pdf
infinity25/IMPORTANT_PDF/DATE OPERATION AND STUDENT DETAILS SHOW USING GRIDVIEW/ASPX.pdf
infinity25/IMPORTANT_PDF/DATE OPERATION AND STUDENT DETAILS SHOW USING GRIDVIEW/ASPX2.pdf
infinity25/IMPORTANT_PDF/DATE OPERATION AND STUDENT DETAILS SHOW USING GRIDVIEW/CS.pdf
infinity25/IMPORTANT_PDF/DATE OPERATION AND STUDENT DETAILS SHOW USING GRIDVIEW/CS2.pdf
infinity25/IMPORTANT_PDF/DATE OPERATION AND STUDENT DETAILS SHOW USING GRIDVIEW/DB.pdf
infinity25-0.1.0.dist-info/LICENSE
infinity25-0.1.0.dist-info/METADATA
infinity25-0.1.0.dist-info/WHEEL
infinity25-0.1.0.dist-info/top_level.txt
infinity25-0.1.0.dist-info/RECORD
