Metadata-Version: 2.1
Name: infinity25
Version: 0.1.0
Summary: A description of your project
Home-page: https://pypi.org/project/infinity/
Author: Your Name
Author-email: your-email@example.com
Classifier: Programming Language :: Python :: 3
Classifier: License :: OSI Approved :: MIT License
Classifier: Operating System :: OS Independent
Requires-Python: >=3.6
License-File: LICENSE
